6.Registers/regN.v
// data_out is continuous and data read when wr = 1;
module regN (data_in,data_out,clk,wr,rst);

parameter N = 8;

input [N-1:0] data_in;
input clk,rst;
input wr;
output [N-1:0] data_out;

reg [N-1:0] register;

//reset behavior, async
always @ (rst) begin
    if(rst)
        register <= 0;
end

//write behavior
always @ (posedge clk) begin
    if(!rst && wr)
        register <= data_in;
end

//read behavior
assign data_out = register;

endmodule // regNdata_in,data_out,clk,wr,rst

6.Registers/tb_regN.v
module tb_regN();

parameter N = 8;
reg [N-1:0] data_in;
reg clk,rst,wr;

wire [N-1:0] data_out;

regN registerN (data_in,data_out,clk,wr,rst);

//reset behavior, clear the reg
initial begin
    rst = 0;
    #1 rst = 1;
    #1 rst = 0;
end

//clock
initial begin
    clk = 0;
    forever #10 clk = ~clk;
end

//write and read

// * for the write signal to occur at every alternate clock edge, this loop shall have a total delay of 2Tp, otherwise the whole thing gets shifted!

initial begin
    wr = 0;
    #5;
    repeat(10) begin
        wr = 1;
        data_in = $random%256;
        #10; //posedge arrives at 10, keep on till 15, then off for one cycle
        wr = 0;
        #30;
    end
    $finish;
end

//gtkwave stuff
initial begin
    $dumpfile("tb_regN.vcd");
    $dumpvars(0,tb_regN);
end


endmodule

6.Registers/tb_regN.vcd
$date
	Fri Mar  6 16:54:21 2020
$end
$version
	Icarus Verilog
$end
$timescale
	1s
$end
$scope module tb_regN $end
$var wire 8 ! data_out [7:0] $end
$var reg 1 " clk $end
$var reg 8 # data_in [7:0] $end
$var reg 1 $ rst $end
$var reg 1 % wr $end
$scope module registerN $end
$var wire 1 " clk $end
$var wire 8 & data_in [7:0] $end
$var wire 8 ' data_out [7:0] $end
$var wire 1 $ rst $end
$var wire 1 % wr $end
$var reg 8 ( register [7:0] $end
$upscope $end
$upscope $end
$enddefinitions $end
#0
$dumpvars
bx (
bx '
bx &
0%
0$
bx #
0"
bx !
$end
#1
b0 !
b0 '
b0 (
1$
#2
0$
#5
b100100 #
b100100 &
1%
#10
b100100 !
b100100 '
b100100 (
1"
#15
0%
#20
0"
#30
1"
#40
0"
#45
b10000001 #
b10000001 &
1%
#50
b10000001 !
b10000001 '
b10000001 (
1"
#55
0%
#60
0"
#70
1"
#80
0"
#85
b1001 #
b1001 &
1%
#90
b1001 !
b1001 '
b1001 (
1"
#95
0%
#100
0"
#110
1"
#120
0"
#125
b1100011 #
b1100011 &
1%
#130
b1100011 !
b1100011 '
b1100011 (
1"
#135
0%
#140
0"
#150
1"
#160
0"
#165
b1101 #
b1101 &
1%
#170
b1101 !
b1101 '
b1101 (
1"
#175
0%
#180
0"
#190
1"
#200
0"
#205
b10001101 #
b10001101 &
1%
#210
b10001101 !
b10001101 '
b10001101 (
1"
#215
0%
#220
0"
#230
1"
#240
0"
#245
b1100101 #
b1100101 &
1%
#250
b1100101 !
b1100101 '
b1100101 (
1"
#255
0%
#260
0"
#270
1"
#280
0"
#285
b10010 #
b10010 &
1%
#290
b10010 !
b10010 '
b10010 (
1"
#295
0%
#300
0"
#310
1"
#320
0"
#325
b1 #
b1 &
1%
#330
b1 !
b1 '
b1 (
1"
#335
0%
#340
0"
#350
1"
#360
0"
#365
b1101 #
b1101 &
1%
#370
b1101 !
b1101 '
b1101 (
1"
#375
0%
