5.ZDC-FSM/Mealy_Zero_Detector.v
module Mealy_Zero_Detector(
    output reg y_out,
    input x_in, clock, reset
    );

    // this is mealy so needs combi+seq part
    reg [1:0] state, next_state;
    parameter  S0 = 2'b00, S1 = 2'b01, S2 = 2'b10, S3 = 2'b11;

    // 3 always blocks - 1 for ns, 1 for yout, 1 to change state

    //1 - output, y_out
    always @(state,x_in)
        case (state)
            S0: y_out = 0;
            S1,S2,S3: y_out = ~x_in;
        endcase

    //2 - next_state
    always @ (state,x_in)
        case (state)
            S0: if (x_in) next_state = S1; else next_state = S0;
            S1: if (x_in) next_state = S3; else next_state = S0;
            S2: if (~x_in) next_state = S0; else next_state = S2;
            S3: if (x_in) next_state = S2; else next_state = S0;
        endcase

    //3 - update state at clk egde
    always @ (posedge clock, negedge reset )
        begin
            if (!reset == 0) state <= S0;
            else state <= next_state;
        end
endmodule

5.ZDC-FSM/tb_Mealy_Zero_Detector.v
module tb_Mealy_Zero_Detector();

    wire t_y_out;
    reg t_x_in, t_clock, t_reset;

    Mealy_Zero_Detector M0(t_y_out, t_x_in, t_clock, t_reset);

    initial #200 $finish;
    initial
    begin
        t_clock = 0;

        $dumpfile("Mealy_Zero_Detector.vcd");
        $dumpvars(0,M0);

        forever #5 t_clock = ~t_clock;
    end

    initial begin
        fork
                t_reset = 0;
            #2  t_reset = 1;
            #10 t_x_in = 1;
            #30 t_x_in = 0;
            #40 t_x_in = 1;
            #50 t_x_in = 0;
            #52 t_x_in = 1;     // glitch
            #54 t_x_in = 0;
            #70 t_x_in = 1;
            #80 t_x_in = 0;
            #90 t_x_in = 1;
        join
    end

endmodule

5.ZDC-FSM/Mealy_Zero_Detector.vcd
$date
	Tue Mar  3 00:12:49 2020
$end
$version
	Icarus Verilog
$end
$timescale
	1s
$end
$scope module tb_Mealy_Zero_Detector $end
$scope module M0 $end
$var wire 1 ! clock $end
$var wire 1 " reset $end
$var wire 1 # x_in $end
$var reg 2 $ next_state [1:0] $end
$var reg 2 % state [1:0] $end
$var reg 1 & y_out $end
$upscope $end
$upscope $end
$enddefinitions $end
#0
$dumpvars
x&
bx %
bx $
x#
0"
0!
$end
#2
1"
#5
b0 $
0&
b0 %
1!
#10
b1 $
0!
1#
#15
1!
#20
0!
#25
1!
#30
b0 $
0!
0#
#35
1!
#40
b1 $
0!
1#
#45
1!
#50
b0 $
0!
0#
#52
b1 $
1#
#54
b0 $
0#
#55
1!
#60
0!
#65
1!
#70
b1 $
0!
1#
#75
1!
#80
b0 $
0!
0#
#85
1!
#90
b1 $
0!
1#
