4.FFs/dff.v
//DFF without reset

module D_FF(input D,Clk,rst, output reg Q);

    // Q = 0 when reset
    always @(posedge Clk, negedge rst)
        if(!rst)    Q <= 1'b0;
        else        Q <= D;
endmodule

4.FFs/jkff_dff.v

module jkff_dff(input J,K,Clk,rst,output Q);

    wire D;
    assign D = (!Q & J)|(!K & Q);

    D_FF dff(D,Clk,rst,Q);

endmodule

4.FFs/tb_jkff_dff.v
module tb_jkff_dff();

    reg J,K,Clk,rst;
    wire Q;

    jkff_dff tff1(J,K,Clk,rst,Q);

    //reset
    initial begin
        rst = 1;
        #1 rst = 0;
        // make negedge
        #1 rst = 1;
    end

    //clock
    initial begin
        $dumpfile("jkff_dff.vcd");
        $dumpvars(0,tb_jkff_dff);

        Clk = 0;
        forever #5 Clk = ~Clk;
    end

    //input
    initial begin
        J = 0; K=0;
        #10 J = 0; K=1;
        #10 J = 1; K =0;
        #10 J = 1; K = 1;
        #10 $finish;
    end
endmodule

4.FFs/jkff_dff.vcd
$date
	Mon Mar  2 22:51:26 2020
$end
$version
	Icarus Verilog
$end
$timescale
	1s
$end
$scope module tb_jkff_dff $end
$var wire 1 ! Q $end
$var reg 1 " Clk $end
$var reg 1 # J $end
$var reg 1 $ K $end
$var reg 1 % rst $end
$scope module tff1 $end
$var wire 1 " Clk $end
$var wire 1 & D $end
$var wire 1 # J $end
$var wire 1 $ K $end
$var wire 1 % rst $end
$var wire 1 ! Q $end
$scope module dff $end
$var wire 1 " Clk $end
$var wire 1 & D $end
$var wire 1 % rst $end
$var reg 1 ! Q $end
$upscope $end
$upscope $end
$upscope $end
$enddefinitions $end
#0
$dumpvars
x&
1%
0$
0#
0"
x!
$end
#1
0&
0!
0%
#2
1%
#5
1"
#10
0"
1$
#15
1"
#20
1&
0"
0$
1#
#25
1!
1"
#30
0&
0"
1$
#35
1&
0!
1"
