2.FA/FA_always.v
// FA

module FA_always(sum, carry_out, a, b, carry_in);
    
    input a,b,carry_in;
    output reg sum, carry_out;
    /* inside @always block only regs can be assigned
    also without reg written, input output is defaulted 
    to a wire */
  
    always @(a,b,carry_in)  //sensitivity list, always @* means all signals
        begin
            sum = (~a & ~b & carry_in) | (~a & b & ~carry_in) | (a & ~b & ~carry_in) | (a & b & carry_in);
            carry_out = (a & b) | (b & carry_in) | (carry_in & a);
        end
        
endmodule

2.FA/TB_FA.v
// FA

module TB_FA();
    
    // local reg
    reg a,b,carry_in;
    wire sum,carry_out;
    
    //DUT
    FA_always fa_dut(sum,carry_out,a,b,carry_in);
    
    initial
    begin
        
        $monitor($time,".a : %b b: %b carry_in : %b sum : %b carry_out : %b",a,b,carry_in,sum,carry_out);
        
        $dumpfile("fa.vcd");
        $dumpvars(0,TB_FA);
        
           a=0;b=0;carry_in=0;
        #5 a=0;b=0;carry_in=1;
        #5 a=0;b=1;carry_in=0;
        #5 a=0;b=1;carry_in=1;
        #5 a=1;b=0;carry_in=0;
        #5 a=1;b=0;carry_in=1;
        #5 a=1;b=1;carry_in=0;
        #5 a=1;b=1;carry_in=1;
        
        #10 $finish;
        
    end
    
endmodule

2.FA/fa.vcd
$date
	Sun Jan 19 17:26:57 2020
$end
$version
	Icarus Verilog
$end
$timescale
	1s
$end
$scope module TB_FA $end
$var wire 1 ! sum $end
$var wire 1 " carry_out $end
$var reg 1 # a $end
$var reg 1 $ b $end
$var reg 1 % carry_in $end
$scope module fa_dut $end
$var wire 1 # a $end
$var wire 1 $ b $end
$var wire 1 % carry_in $end
$var reg 1 " carry_out $end
$var reg 1 ! sum $end
$upscope $end
$upscope $end
$enddefinitions $end
#0
$dumpvars
0%
0$
0#
0"
0!
$end
#5
1!
1%
#10
0%
1$
#15
1"
0!
1%
#20
0"
1!
0%
0$
1#
#25
1"
0!
1%
#30
0%
1$
#35
1!
1%
